YixiaoshiManhuaChanlunShizhanfa/README.md
YixiaoshiManhuaChanlunShizhanfa/__init__.py
YixiaoshiManhuaChanlunShizhanfa/__main__.py
YixiaoshiManhuaChanlunShizhanfa/file.epub
YixiaoshiManhuaChanlunShizhanfa/index.html
YixiaoshiManhuaChanlunShizhanfa/css/__init__.py
YixiaoshiManhuaChanlunShizhanfa/css/annotations.css
YixiaoshiManhuaChanlunShizhanfa/css/main.css
YixiaoshiManhuaChanlunShizhanfa/css/normalize.css
YixiaoshiManhuaChanlunShizhanfa/css/popup.css
YixiaoshiManhuaChanlunShizhanfa/font/__init__.py
YixiaoshiManhuaChanlunShizhanfa/font/fontello.eot
YixiaoshiManhuaChanlunShizhanfa/font/fontello.svg
YixiaoshiManhuaChanlunShizhanfa/font/fontello.ttf
YixiaoshiManhuaChanlunShizhanfa/font/fontello.woff
YixiaoshiManhuaChanlunShizhanfa/img/__init__.py
YixiaoshiManhuaChanlunShizhanfa/img/annotator-glyph-sprite.png
YixiaoshiManhuaChanlunShizhanfa/img/annotator-icon-sprite.png
YixiaoshiManhuaChanlunShizhanfa/img/apple-touch-icon.png
YixiaoshiManhuaChanlunShizhanfa/img/cancelfullscreen.png
YixiaoshiManhuaChanlunShizhanfa/img/close.png
YixiaoshiManhuaChanlunShizhanfa/img/fullscreen.png
YixiaoshiManhuaChanlunShizhanfa/img/loader.gif
YixiaoshiManhuaChanlunShizhanfa/img/menu-icon.png
YixiaoshiManhuaChanlunShizhanfa/img/save.png
YixiaoshiManhuaChanlunShizhanfa/img/saved.png
YixiaoshiManhuaChanlunShizhanfa/img/settings-s.png
YixiaoshiManhuaChanlunShizhanfa/img/settings.png
YixiaoshiManhuaChanlunShizhanfa/img/star.png
YixiaoshiManhuaChanlunShizhanfa/js/__init__.py
YixiaoshiManhuaChanlunShizhanfa/js/epub.js
YixiaoshiManhuaChanlunShizhanfa/js/epub.min.js
YixiaoshiManhuaChanlunShizhanfa/js/epub.min.map
YixiaoshiManhuaChanlunShizhanfa/js/hooks.min.js
YixiaoshiManhuaChanlunShizhanfa/js/hooks.min.map
YixiaoshiManhuaChanlunShizhanfa/js/reader.js
YixiaoshiManhuaChanlunShizhanfa/js/reader.js.map
YixiaoshiManhuaChanlunShizhanfa/js/reader.min.js
YixiaoshiManhuaChanlunShizhanfa/js/reader.min.map
YixiaoshiManhuaChanlunShizhanfa/js/hooks/__init__.py
yixiaoshi_manhua_chanlun_shizhanfa-2022.10.15.0.dist-info/METADATA
yixiaoshi_manhua_chanlun_shizhanfa-2022.10.15.0.dist-info/WHEEL
yixiaoshi_manhua_chanlun_shizhanfa-2022.10.15.0.dist-info/entry_points.txt
yixiaoshi_manhua_chanlun_shizhanfa-2022.10.15.0.dist-info/top_level.txt
yixiaoshi_manhua_chanlun_shizhanfa-2022.10.15.0.dist-info/RECORD
